{
  "/(auth)/login/page": "app/(auth)/login/page.js",
  "/(dashboard)/super-admin/konfigurasi/page": "app/(dashboard)/super-admin/konfigurasi/page.js",
  "/(dashboard)/petugas/prediksi/page": "app/(dashboard)/petugas/prediksi/page.js",
  "/(dashboard)/super-admin/kelola-data/page": "app/(dashboard)/super-admin/kelola-data/page.js",
  "/(dashboard)/petugas/dashboard/page": "app/(dashboard)/petugas/dashboard/page.js",
  "/(dashboard)/super-admin/kelola-user/page": "app/(dashboard)/super-admin/kelola-user/page.js"
}